gpt_review_with_precondition/__init__.py
gpt_review_with_precondition/args/__init__.py
gpt_review_with_precondition/args/args.py
gpt_review_with_precondition/args/env.py
gpt_review_with_precondition/llama_index_wrapper/__init__.py
gpt_review_with_precondition/llama_index_wrapper/api.py
gpt_review_with_precondition/llama_index_wrapper/notion.py
gpt_review_with_precondition/review.py
gpt_review_with_precondition/save.py
gpt_review_with_precondition/storage/__init__.py
gpt_review_with_precondition/storage/storage.py
gpt_review_with_precondition/zip/__init__.py
gpt_review_with_precondition/zip/zip.py
gpt_review_with_precondition-0.3.8.dist-info/METADATA
gpt_review_with_precondition-0.3.8.dist-info/WHEEL
gpt_review_with_precondition-0.3.8.dist-info/entry_points.txt
gpt_review_with_precondition-0.3.8.dist-info/RECORD
