Metadata-Version: 2.1
Name: gpt-review-with-precondition
Version: 0.3.8
Summary: GPT review with precondition from Notion
License: MIT
Author: wakuwaku3
Author-email: takushi.yokoyama@sansan.com
Requires-Python: >=3.11,<3.12
Classifier: License :: OSI Approved :: MIT License
Classifier: Programming Language :: Python :: 3
Classifier: Programming Language :: Python :: 3.11
Requires-Dist: google-cloud-storage (>=2.12.0,<3.0.0)
Requires-Dist: llama-index (>=0.8.48,<0.9.0)
Requires-Dist: poetry (>=1.6.1,<2.0.0)
Requires-Dist: setuptools (>=68.2.2,<69.0.0)
